lion/__init__.py
lion/peer.py
pylion_yellowakita-0.0.1.dist-info/LICENSE.md
pylion_yellowakita-0.0.1.dist-info/METADATA
pylion_yellowakita-0.0.1.dist-info/WHEEL
pylion_yellowakita-0.0.1.dist-info/top_level.txt
pylion_yellowakita-0.0.1.dist-info/RECORD
