Metadata-Version: 2.1
Name: pylion-yellowakita
Version: 0.0.1
Summary: Uma biblioteca simples para comunicação p2p na rede local
Author: Marcel Guinhos
Author-email: mguinhos@gmail.com
License: UNKNOWN
Platform: UNKNOWN
Requires-Python: >=3.8
License-File: LICENSE.md
